django_geocad/__init__.py
django_geocad/admin.py
django_geocad/apps.py
django_geocad/models.py
django_geocad/urls.py
django_geocad/views.py
django_geocad/management/commands/__init__.py
django_geocad/management/commands/populate_block_field.py
django_geocad/migrations/0001_initial.py
django_geocad/migrations/0002_alter_drawing_options_drawing_designx_and_more.py
django_geocad/migrations/0003_layer.py
django_geocad/migrations/0004_entity.py
django_geocad/migrations/0005_entity_block.py
django_geocad/migrations/0006_entitydata.py
django_geocad/migrations/0007_entity_rotation_entity_xscale_entity_yscale.py
django_geocad/migrations/0008_alter_entity_data.py
django_geocad/migrations/0009_alter_entity_geom.py
django_geocad/migrations/0010_layer_unique_layer_name.py
django_geocad/migrations/__init__.py
django_geocad/static/django_geocad/js/change_script.js
django_geocad/static/django_geocad/js/htmx.min.js
django_geocad/static/django_geocad/js/map_script.js
django_geocad/templates/django_geocad/base.html
django_geocad/templates/django_geocad/drawing_detail.html
django_geocad/templates/django_geocad/drawing_list.html
django_geocad/templates/django_geocad/entity_change.html
django_geocad/templates/django_geocad/entity_create.html
django_geocad/templates/django_geocad/map_data.html
django_geocad/templates/django_geocad/htmx/drawing_detail.html
django_geocad/templates/django_geocad/htmx/entity_data_list.html
django_geocad-0.9.0.dist-info/METADATA
django_geocad-0.9.0.dist-info/WHEEL
django_geocad-0.9.0.dist-info/licenses/LICENSE
django_geocad-0.9.0.dist-info/RECORD
