Metadata-Version: 2.4
Name: django-geocad
Version: 0.9.0
Summary: Django app that imports CAD drawings in Leaflet.js maps
Project-URL: Repository, https://github.com/andywar65/django-geocad
Author-email: andywar65 <andy.war1965@gmail.com>
License: MIT License
License-File: LICENSE
Classifier: Framework :: Django
Classifier: Operating System :: OS Independent
Classifier: Programming Language :: Python :: 3 :: Only
Classifier: Programming Language :: Python :: 3.10
Classifier: Programming Language :: Python :: 3.11
Classifier: Programming Language :: Python :: 3.12
Classifier: Programming Language :: Python :: 3.13
Requires-Python: >=3.14
Requires-Dist: django-colorfield
Requires-Dist: django-geojson
Requires-Dist: django-leaflet
Requires-Dist: django>=4.2
Requires-Dist: easy-thumbnails
Requires-Dist: ezdxf
Requires-Dist: nh3
Requires-Dist: pyproj
Requires-Dist: shapely
